odoo/addons/delivery_postlogistics/README.rst
odoo/addons/delivery_postlogistics/__init__.py
odoo/addons/delivery_postlogistics/__manifest__.py
odoo/addons/delivery_postlogistics/data/barcode handbuch.PDF
odoo/addons/delivery_postlogistics/data/delivery.xml
odoo/addons/delivery_postlogistics/data/partner.xml
odoo/addons/delivery_postlogistics/data/product.xml
odoo/addons/delivery_postlogistics/i18n/delivery_postlogistics.pot
odoo/addons/delivery_postlogistics/migrations/13.0.1.0.0/pre-migration.py
odoo/addons/delivery_postlogistics/models/__init__.py
odoo/addons/delivery_postlogistics/models/delivery_carrier.py
odoo/addons/delivery_postlogistics/models/postlogistics_carrier_template_options.py
odoo/addons/delivery_postlogistics/models/postlogistics_license.py
odoo/addons/delivery_postlogistics/models/postlogistics_shipping_label.py
odoo/addons/delivery_postlogistics/models/product_packaging.py
odoo/addons/delivery_postlogistics/models/res_partner.py
odoo/addons/delivery_postlogistics/models/stock_move.py
odoo/addons/delivery_postlogistics/models/stock_picking.py
odoo/addons/delivery_postlogistics/models/stock_quant_package.py
odoo/addons/delivery_postlogistics/postlogistics/__init__.py
odoo/addons/delivery_postlogistics/postlogistics/web_service.py
odoo/addons/delivery_postlogistics/readme/CONFIGURE.rst
odoo/addons/delivery_postlogistics/readme/CONTRIBUTORS.rst
odoo/addons/delivery_postlogistics/readme/CREDITS.rst
odoo/addons/delivery_postlogistics/readme/DESCRIPTION.rst
odoo/addons/delivery_postlogistics/readme/ROADMAP.rst
odoo/addons/delivery_postlogistics/security/ir.model.access.csv
odoo/addons/delivery_postlogistics/static/description/icon.svg
odoo/addons/delivery_postlogistics/static/description/index.html
odoo/addons/delivery_postlogistics/static/img/postlogistics-logo.jpg
odoo/addons/delivery_postlogistics/tests/__init__.py
odoo/addons/delivery_postlogistics/tests/common.py
odoo/addons/delivery_postlogistics/tests/test_packaging_code.py
odoo14_addon_delivery_postlogistics-14.0.1.1.0.dist-info/METADATA
odoo14_addon_delivery_postlogistics-14.0.1.1.0.dist-info/WHEEL
odoo14_addon_delivery_postlogistics-14.0.1.1.0.dist-info/top_level.txt
odoo14_addon_delivery_postlogistics-14.0.1.1.0.dist-info/RECORD
